scldata/__init__.py
scldata/loader.py
scldata/data/entries.json
scldata/data/labels.json
scldata/data/scl2205.csv
scldata/data/splits.json
p_scldata-2025.6.0.dist-info/METADATA
p_scldata-2025.6.0.dist-info/WHEEL
p_scldata-2025.6.0.dist-info/entry_points.txt
p_scldata-2025.6.0.dist-info/licenses/LICENSE
p_scldata-2025.6.0.dist-info/RECORD
