Metadata-Version: 2.4
Name: p-scldata
Version: 2025.6.0
Summary: A dataset (SCL2205) for subcellular localisation prediction modelling
Project-URL: Homepage, https://github.com/ousodaniel/scldata
Project-URL: Repository, https://github.com/ousodaniel/scldata.git
Project-URL: Bug Tracker, https://github.com/ousodaniel/scldata/issues
Author-email: "Ouso D. O. S." <daniel.ouso@ucdconnect.ie>, ousodaniel@gmail.com
Maintainer-email: "Ouso D. O. S." <daniel.ouso@ucdconnect.ie>
License-Expression: MIT
License-File: LICENSE
Keywords: classification,clustering,dataset,machine learning,natural language processing,subcellular localisation
Requires-Python: >=3.8
Requires-Dist: pandas
